LICENSE
MANIFEST.in
README.md
pyproject.toml
setup.py
ecquote/__init__.py
ecquote/__main__.py
ecquote/_compat.py
ecquote/area.py
ecquote/cart.py
ecquote/checks.py
ecquote/costing.py
ecquote/grib.py
ecquote/grid.py
ecquote/landsea.py
ecquote/landsea_fixed.py
ecquote/landsea_mask_gg.py
ecquote/landsea_mask_reduced.py
ecquote/landsea_mask_regular.py
ecquote/mars.py
ecquote/matching.py
ecquote/modify.py
ecquote/parser.py
ecquote/repres.py
ecquote/request.py
ecquote/resolution.py
ecquote/resources.py
ecquote/rest.py
ecquote/sets.py
ecquote/testing.py
ecquote/utils.py
ecquote.egg-info/PKG-INFO
ecquote.egg-info/SOURCES.txt
ecquote.egg-info/dependency_links.txt
ecquote.egg-info/entry_points.txt
ecquote.egg-info/requires.txt
ecquote.egg-info/top_level.txt
ecquote.egg-info/zip-safe
ecquote/resources/F1280.json
ecquote/resources/F160.json
ecquote/resources/F200.json
ecquote/resources/F256.json
ecquote/resources/F320.json
ecquote/resources/F400.json
ecquote/resources/F640.json
ecquote/resources/F80.json
ecquote/resources/N128.json
ecquote/resources/N1280.json
ecquote/resources/N160.json
ecquote/resources/N200.json
ecquote/resources/N256.json
ecquote/resources/N320.json
ecquote/resources/N400.json
ecquote/resources/N640.json
ecquote/resources/N80.json
ecquote/resources/O1280.json
ecquote/resources/O160.json
ecquote/resources/O320.json
ecquote/resources/O640.json
ecquote/resources/accuracy.yaml
ecquote/resources/config.yaml
ecquote/resources/data-values-bands.yaml
ecquote/resources/epu-based.yaml
ecquote/resources/free-open-data.diss
ecquote/resources/free-wmo-essential.diss
ecquote/resources/params.yaml
ecquote/resources/pgen-accuracy.yaml
ecquote/resources/reduced-0_125.json
ecquote/resources/reduced-0_25.json
ecquote/resources/reduced-0_5.json
ecquote/resources/regular-0_1.json
ecquote/resources/regular-0_125.json
ecquote/resources/representations.yaml
ecquote/resources/sets.yaml
ecquote/resources/volume-bands.yaml
ecquote/resources/wave-mask-gg.json
ecquote/resources/wave-mask-reduced.json
ecquote/resources/wave-mask-regular.json
ecquote/splitters/__init__.py
ecquote/splitters/canonical.py
ecquote/splitters/category.py
ecquote/splitters/constant.py
ecquote/splitters/destination.py
